{
  "paths": {
    "/gractiveobelisks": {
      "get": {
        "description": "Get all GR Site Active Obelisk entries",
        "summary": "",
        "tags": [
          "Guardian Ruins"
        ],
        "security": []
      },
      "post": {
        "description": "Create a new GR Site Active Obelisk entry",
        "summary": "",
        "tags": [
          "Guardian Ruins"
        ],
        "security": [
          "siteWrite"
        ]
      }
    },
    "/gractiveobelisks/count": {
      "get": {
        "description": "Get a count of all GR Site Active Obelisk entries",
        "summary": "",
        "tags": [
          "Guardian Ruins"
        ],
        "security": []
      }
    },
    "/gractiveobelisks/{id}": {
      "get": {
        "description": "Get a GR Site Active Obelisk by id",
        "summary": "",
        "tags": [
          "Guardian Ruins"
        ],
        "security": []
      },
      "put": {
        "description": "Update a GR Site Active Obelisk by id",
        "summary": "",
        "tags": [
          "Guardian Ruins"
        ],
        "security": [
          "siteWrite"
        ]
      },
      "delete": {
        "description": "Delete a GR Site Active Obelisk by id",
        "summary": "",
        "tags": [
          "Guardian Ruins"
        ],
        "security": [
          "siteDelete"
        ]
      }
    },
    "/gractiveobelisks/{id}/relationships/{relation}": {
      "post": {
        "description": "Create a new record",
        "summary": "",
        "tags": [
          "z.Unused"
        ]
      },
      "put": {
        "description": "Update a record",
        "summary": "",
        "tags": [
          "z.Unused"
        ]
      },
      "delete": {
        "description": "Delete a record",
        "summary": "",
        "tags": [
          "z.Unused"
        ]
      }
    }
  },
  "tags": [
    {
      "name": "Guardian Ruins",
      "description": "Code Name - GR"
    }
  ]
}
