{
  "routes": [
    {
      "method": "GET",
      "path": "/excludecmdrs",
      "handler": "Excludecmdr.find",
      "config": {
        "policies": []
      }
    },
    {
      "method": "GET",
      "path": "/excludecmdrs/count",
      "handler": "Excludecmdr.count",
      "config": {
        "policies": []
      }
    },
    {
      "method": "GET",
      "path": "/excludecmdrs/:id",
      "handler": "Excludecmdr.findOne",
      "config": {
        "policies": []
      }
    },
    {
      "method": "POST",
      "path": "/excludecmdrs",
      "handler": "Excludecmdr.create",
      "config": {
        "policies": []
      }
    },
    {
      "method": "PUT",
      "path": "/excludecmdrs/:id",
      "handler": "Excludecmdr.update",
      "config": {
        "policies": []
      }
    },
    {
      "method": "DELETE",
      "path": "/excludecmdrs/:id",
      "handler": "Excludecmdr.destroy",
      "config": {
        "policies": []
      }
    }
  ]
}
