{
  "paths": {
    "/permitlocks": {
      "get": {
        "description": "Get all Permit Lock entries",
        "summary": "",
        "tags": [
          "Permit Locks"
        ],
        "security": []
      },
      "post": {
        "description": "Create a new Permit Lock entry",
        "summary": "",
        "tags": [
          "Permit Locks"
        ],
        "security": [
          "updateLogWrite"
        ]
      }
    },
    "/permitlocks/count": {
      "get": {
        "description": "Get a count of all Permit Lock entries",
        "summary": "",
        "tags": [
          "Permit Locks"
        ],
        "security": []
      }
    },
    "/permitlocks/{id}": {
      "get": {
        "description": "Get a Permit Lock by id",
        "summary": "",
        "tags": [
          "Permit Locks"
        ],
        "security": []
      },
      "put": {
        "description": "Update a Permit Lock by id",
        "summary": "",
        "tags": [
          "Permit Locks"
        ],
        "security": [
          "updateLogWrite"
        ]
      },
      "delete": {
        "description": "Delete a Permit Lock by id",
        "summary": "",
        "tags": [
          "Permit Locks"
        ],
        "security": [
          "updateLogWrite"
        ]
      }
    }
  },
  "tags": [
    {
      "name": "Permit Locks",
      "description": "Permit locked regions"
    }
  ]
}
